docs/source/conf.py
elevatr/__init__.py
elevatr/downloader.py
elevatr/get_elev_raster.py
elevatr/raster.py
elevatr/raster_operations.py
elevatr/settings.py
elevatr/utils.py
elevatr-0.4.0.dist-info/licenses/LICENSE
elevatr-0.4.0.dist-info/METADATA
elevatr-0.4.0.dist-info/WHEEL
elevatr-0.4.0.dist-info/top_level.txt
elevatr-0.4.0.dist-info/RECORD
