Metadata-Version: 2.4
Name: elevatr
Version: 0.4.0
Summary: A Python package to simplify downloading and processing elevation data.
Author-email: Titouan Le Gourrierec <titouanlegourrierec@icloud.com>
License-Expression: MIT
Project-URL: Homepage, https://github.com/titouanlegourrierec/elevatr
Project-URL: Documentation, https://elevatr.readthedocs.io
Project-URL: Bug Tracker, https://github.com/titouanlegourrierec/elevatr/issues
Classifier: Intended Audience :: Science/Research
Classifier: Intended Audience :: Developers
Classifier: Operating System :: OS Independent
Classifier: Programming Language :: Python :: 3
Classifier: Programming Language :: Python :: 3 :: Only
Classifier: Programming Language :: Python :: 3.9
Classifier: Programming Language :: Python :: 3.10
Classifier: Programming Language :: Python :: 3.11
Classifier: Programming Language :: Python :: 3.12
Classifier: Programming Language :: Python :: 3.13
Classifier: Topic :: Scientific/Engineering :: GIS
Classifier: Topic :: Scientific/Engineering :: Information Analysis
Classifier: Topic :: Scientific/Engineering :: Visualization
Requires-Python: <3.14,>=3.10
License-File: LICENSE
Requires-Dist: contextily>=1.7.0
Requires-Dist: geopandas>=1.1.2
Requires-Dist: ipykernel>=7.1.0
Requires-Dist: pyproj>=3.7.1
Requires-Dist: pyvista>=0.46.4
Requires-Dist: rasterio>=1.4.4
Requires-Dist: requests>=2.32.5
Requires-Dist: rioxarray>=0.19.0
Requires-Dist: tqdm>=4.67.1
Dynamic: license-file
